{
    "Version": "1.1",
    "Data": {
        "Source": "u:\\fps\\intermediate\\build\\win64\\unrealeditor\\inc\\fps\\pickupspawnpoint.gen.cpp",
        "ProvidedModule": "",
        "PCH": "u:\\fps\\intermediate\\build\\win64\\fpseditor\\development\\engine\\sharedpch.engine.shadowerrors.h.pch",
        "Includes": [
            "u:\\fps\\intermediate\\build\\win64\\unrealeditor\\development\\fps\\definitions.fps.h",
            "u:\\fps\\source\\fps\\pickups\\pickupspawnpoint.h",
            "u:\\fps\\intermediate\\build\\win64\\unrealeditor\\inc\\fps\\pickupspawnpoint.generated.h"
        ],
        "ImportedModules": [],
        "ImportedHeaderUnits": []
    }
}